<?xml version="1.0" encoding="UTF-8"?>
<sv:node xmlns:sv="http://www.jcp.org/jcr/sv/1.0" xmlns:xsi="http://www.w3.org/2001/XMLSchema-instance" sv:name="Matthew">
  <sv:property sv:name="jcr:primaryType" sv:type="Name">
    <sv:value>mgnl:folder</sv:value>
  </sv:property>
  <sv:property sv:name="jcr:mixinTypes" sv:type="Name" sv:multiple="true">
    <sv:value>mgnl:hasVersion</sv:value>
  </sv:property>
  <sv:property sv:name="jcr:uuid" sv:type="String">
    <sv:value>0ced0ed3-0d31-4ae9-b749-f50f457f5670</sv:value>
  </sv:property>
  <sv:property sv:name="mgnl:activationStatus" sv:type="Boolean">
    <sv:value>true</sv:value>
  </sv:property>
  <sv:property sv:name="mgnl:created" sv:type="Date">
    <sv:value>2020-06-01T22:21:53.907-05:00</sv:value>
  </sv:property>
  <sv:property sv:name="mgnl:createdBy" sv:type="String">
    <sv:value>superuser</sv:value>
  </sv:property>
  <sv:property sv:name="mgnl:lastActivated" sv:type="Date">
    <sv:value>2020-06-01T22:23:34.809-05:00</sv:value>
  </sv:property>
  <sv:property sv:name="mgnl:lastActivatedBy" sv:type="String">
    <sv:value>superuser</sv:value>
  </sv:property>
  <sv:property sv:name="mgnl:lastActivatedVersion" sv:type="String">
    <sv:value>1.0</sv:value>
  </sv:property>
  <sv:property sv:name="mgnl:lastActivatedVersionCreated" sv:type="Date">
    <sv:value>2020-06-01T22:23:15.434-05:00</sv:value>
  </sv:property>
  <sv:property sv:name="mgnl:lastModified" sv:type="Date">
    <sv:value>2020-06-01T22:23:09.430-05:00</sv:value>
  </sv:property>
  <sv:property sv:name="mgnl:lastModifiedBy" sv:type="String">
    <sv:value>superuser</sv:value>
  </sv:property>
  <sv:node sv:name="Logarithms">
    <sv:property sv:name="jcr:primaryType" sv:type="Name">
      <sv:value>mgnl:content</sv:value>
    </sv:property>
    <sv:property sv:name="jcr:mixinTypes" sv:type="Name" sv:multiple="true">
      <sv:value>mgnl:hasVersion</sv:value>
    </sv:property>
    <sv:property sv:name="jcr:uuid" sv:type="String">
      <sv:value>6856d446-3d3e-48f2-af05-1f2e63270286</sv:value>
    </sv:property>
    <sv:property sv:name="attachment" sv:type="String">
      <sv:value>jcr:e1fd7e54-8dd0-4f73-9133-08f719e9df83</sv:value>
    </sv:property>
    <sv:property sv:name="author" sv:type="String">
      <sv:value>Matthew Ru</sv:value>
    </sv:property>
    <sv:property sv:name="content" sv:type="String">
      <sv:value>&lt;p&gt;fake study guide&lt;/p&gt;
</sv:value>
    </sv:property>
    <sv:property sv:name="course" sv:type="String">
      <sv:value>HA2</sv:value>
    </sv:property>
    <sv:property sv:name="courseTypes" sv:type="String" sv:multiple="true">
      <sv:value>b1691bf9-0277-469c-a000-f82cb8a92751</sv:value>
    </sv:property>
    <sv:property sv:name="lastModified" sv:type="Date">
      <sv:value>2020-06-01T00:00:00.000-05:00</sv:value>
    </sv:property>
    <sv:property sv:name="mgnl:activationStatus" sv:type="Boolean">
      <sv:value>true</sv:value>
    </sv:property>
    <sv:property sv:name="mgnl:created" sv:type="Date">
      <sv:value>2020-06-01T22:23:09.431-05:00</sv:value>
    </sv:property>
    <sv:property sv:name="mgnl:createdBy" sv:type="String">
      <sv:value>superuser</sv:value>
    </sv:property>
    <sv:property sv:name="mgnl:lastActivated" sv:type="Date">
      <sv:value>2020-06-01T22:23:41.688-05:00</sv:value>
    </sv:property>
    <sv:property sv:name="mgnl:lastActivatedBy" sv:type="String">
      <sv:value>superuser</sv:value>
    </sv:property>
    <sv:property sv:name="mgnl:lastActivatedVersion" sv:type="String">
      <sv:value>1.0</sv:value>
    </sv:property>
    <sv:property sv:name="mgnl:lastActivatedVersionCreated" sv:type="Date">
      <sv:value>2020-06-01T22:23:41.341-05:00</sv:value>
    </sv:property>
    <sv:property sv:name="mgnl:lastModified" sv:type="Date">
      <sv:value>2020-06-01T22:23:09.431-05:00</sv:value>
    </sv:property>
    <sv:property sv:name="mgnl:lastModifiedBy" sv:type="String">
      <sv:value>superuser</sv:value>
    </sv:property>
    <sv:property sv:name="name" sv:type="String">
      <sv:value>Logarithms</sv:value>
    </sv:property>
    <sv:property sv:name="schools" sv:type="String" sv:multiple="true">
      <sv:value>51d34af8-37e0-44ff-b3ea-3db51871a64e</sv:value>
    </sv:property>
  </sv:node>
</sv:node>
